[
    {
        "driverId": "ahrens",
        "url": "http://en.wikipedia.org/wiki/Kurt_Ahrens,_Jr.",
        "givenName": "Kurt",
        "familyName": "Ahrens",
        "dateOfBirth": "1940-04-19",
        "nationality": "German"
    },
    {
        "driverId": "jack_brabham",
        "url": "http://en.wikipedia.org/wiki/Jack_Brabham",
        "givenName": "Jack",
        "familyName": "Brabham",
        "dateOfBirth": "1926-04-02",
        "nationality": "Australian"
    },
    {
        "driverId": "charlton",
        "url": "http://en.wikipedia.org/wiki/Dave_Charlton",
        "givenName": "Dave",
        "familyName": "Charlton",
        "dateOfBirth": "1936-10-27",
        "nationality": "South African"
    },
    {
        "driverId": "gurney",
        "url": "http://en.wikipedia.org/wiki/Dan_Gurney",
        "givenName": "Dan",
        "familyName": "Gurney",
        "dateOfBirth": "1931-04-13",
        "nationality": "American"
    },
    {
        "driverId": "love",
        "url": "http://en.wikipedia.org/wiki/John_Love_(racing_driver)",
        "givenName": "John",
        "familyName": "Love",
        "dateOfBirth": "1924-12-07",
        "nationality": "Rhodesian"
    },
    {
        "driverId": "moser",
        "url": "http://en.wikipedia.org/wiki/Silvio_Moser",
        "givenName": "Silvio",
        "familyName": "Moser",
        "dateOfBirth": "1941-04-24",
        "nationality": "Swiss"
    },
    {
        "driverId": "rindt",
        "url": "http://en.wikipedia.org/wiki/Jochen_Rindt",
        "givenName": "Jochen",
        "familyName": "Rindt",
        "dateOfBirth": "1942-04-18",
        "nationality": "Austrian"
    }
]