[
    {
        "driverId": "barrichello",
        "code": "BAR",
        "url": "http://en.wikipedia.org/wiki/Rubens_Barrichello",
        "givenName": "Rubens",
        "familyName": "Barrichello",
        "dateOfBirth": "1972-05-23",
        "nationality": "Brazilian"
    },
    {
        "driverId": "magnussen",
        "code": "MAG",
        "url": "http://en.wikipedia.org/wiki/Jan_Magnussen",
        "givenName": "Jan",
        "familyName": "Magnussen",
        "dateOfBirth": "1973-07-04",
        "nationality": "Danish"
    },
    {
        "driverId": "verstappen",
        "url": "http://en.wikipedia.org/wiki/Jos_Verstappen",
        "givenName": "Jos",
        "familyName": "Verstappen",
        "dateOfBirth": "1972-03-04",
        "nationality": "Dutch"
    }
]