[
    {
        "driverId": "doohan",
        "permanentNumber": "61",
        "code": "DOO",
        "url": "http://en.wikipedia.org/wiki/Jack_Doohan",
        "givenName": "Jack",
        "familyName": "Doohan",
        "dateOfBirth": "2003-01-20",
        "nationality": "Australian"
    },
    {
        "driverId": "gasly",
        "permanentNumber": "10",
        "code": "GAS",
        "url": "http://en.wikipedia.org/wiki/Pierre_Gasly",
        "givenName": "Pierre",
        "familyName": "Gasly",
        "dateOfBirth": "1996-02-07",
        "nationality": "French"
    },
    {
        "driverId": "ocon",
        "permanentNumber": "31",
        "code": "OCO",
        "url": "http://en.wikipedia.org/wiki/Esteban_Ocon",
        "givenName": "Esteban",
        "familyName": "Ocon",
        "dateOfBirth": "1996-09-17",
        "nationality": "French"
    }
]