{
  "driverId": "blundell",
  "finalStandings": {
    "1991": {
      "year": "1991",
      "position": "19",
      "points": "1"
    },
    "1993": {
      "year": "1993",
      "position": "10",
      "points": "10"
    },
    "1994": {
      "year": "1994",
      "position": "12",
      "points": "8"
    },
    "1995": {
      "year": "1995",
      "position": "10",
      "points": "13"
    }
  },
  "posAfterRace": {
    "1991": {
      "year": "1991",
      "pos": {
        "United States Grand Prix": {
          "points": 0
        },
        "Brazilian Grand Prix": {
          "points": 0
        },
        "San Marino Grand Prix": {
          "points": 0
        },
        "Monaco Grand Prix": {
          "points": 0
        },
        "Canadian Grand Prix": {
          "points": 0
        },
        "Mexican Grand Prix": {
          "points": 0
        },
        "French Grand Prix": {
          "points": 0
        },
        "British Grand Prix": {
          "points": 0
        },
        "German Grand Prix": {
          "points": 0
        },
        "Hungarian Grand Prix": {
          "points": 0
        },
        "Belgian Grand Prix": {
          "points": 1
        },
        "Italian Grand Prix": {
          "points": 1
        },
        "Portuguese Grand Prix": {
          "points": 1
        },
        "Spanish Grand Prix": {
          "points": 1
        },
        "Japanese Grand Prix": {
          "points": 1
        },
        "Australian Grand Prix": {
          "points": 1
        }
      }
    },
    "1993": {
      "year": "1993",
      "pos": {
        "South African Grand Prix": {
          "points": 4
        },
        "Brazilian Grand Prix": {
          "points": 6
        },
        "European Grand Prix": {
          "points": 6
        },
        "San Marino Grand Prix": {
          "points": 6
        },
        "Spanish Grand Prix": {
          "points": 6
        },
        "Monaco Grand Prix": {
          "points": 6
        },
        "Canadian Grand Prix": {
          "points": 6
        },
        "French Grand Prix": {
          "points": 6
        },
        "British Grand Prix": {
          "points": 6
        },
        "German Grand Prix": {
          "points": 10
        },
        "Hungarian Grand Prix": {
          "points": 10
        },
        "Belgian Grand Prix": {
          "points": 10
        },
        "Italian Grand Prix": {
          "points": 10
        },
        "Portuguese Grand Prix": {
          "points": 10
        },
        "Japanese Grand Prix": {
          "points": 10
        },
        "Australian Grand Prix": {
          "points": 10
        }
      }
    },
    "1994": {
      "year": "1994",
      "pos": {
        "Brazilian Grand Prix": {
          "points": 0
        },
        "Pacific Grand Prix": {
          "points": 0
        },
        "San Marino Grand Prix": {
          "points": 0
        },
        "Monaco Grand Prix": {
          "points": 0
        },
        "Spanish Grand Prix": {
          "points": 4
        },
        "Canadian Grand Prix": {
          "points": 4
        },
        "French Grand Prix": {
          "points": 4
        },
        "British Grand Prix": {
          "points": 4
        },
        "German Grand Prix": {
          "points": 4
        },
        "Hungarian Grand Prix": {
          "points": 6
        },
        "Belgian Grand Prix": {
          "points": 8
        },
        "Italian Grand Prix": {
          "points": 8
        },
        "Portuguese Grand Prix": {
          "points": 8
        },
        "European Grand Prix": {
          "points": 8
        },
        "Japanese Grand Prix": {
          "points": 8
        },
        "Australian Grand Prix": {
          "points": 8
        }
      }
    },
    "1995": {
      "year": "1995",
      "pos": {
        "Brazilian Grand Prix": {
          "points": 1
        },
        "Argentine Grand Prix": {
          "points": 1
        },
        "Monaco Grand Prix": {
          "points": 3
        },
        "Canadian Grand Prix": {
          "points": 3
        },
        "French Grand Prix": {
          "points": 3
        },
        "British Grand Prix": {
          "points": 5
        },
        "German Grand Prix": {
          "points": 5
        },
        "Hungarian Grand Prix": {
          "points": 5
        },
        "Belgian Grand Prix": {
          "points": 7
        },
        "Italian Grand Prix": {
          "points": 10
        },
        "Portuguese Grand Prix": {
          "points": 10
        },
        "European Grand Prix": {
          "points": 10
        },
        "Pacific Grand Prix": {
          "points": 10
        },
        "Japanese Grand Prix": {
          "points": 10
        },
        "Australian Grand Prix": {
          "points": 13
        }
      }
    }
  },
  "racePosition": {
    "1991": {
      "year": "1991",
      "positions": {
        "United States Grand Prix": "22",
        "Brazilian Grand Prix": "17",
        "San Marino Grand Prix": "8",
        "Monaco Grand Prix": "18",
        "Canadian Grand Prix": "29",
        "Mexican Grand Prix": "13",
        "French Grand Prix": "18",
        "British Grand Prix": "15",
        "German Grand Prix": "12",
        "Hungarian Grand Prix": "19",
        "Belgian Grand Prix": "6",
        "Italian Grand Prix": "12",
        "Portuguese Grand Prix": "25",
        "Spanish Grand Prix": "18",
        "Japanese Grand Prix": "31",
        "Australian Grand Prix": "17"
      }
    },
    "1993": {
      "year": "1993",
      "positions": {
        "South African Grand Prix": "3",
        "Brazilian Grand Prix": "5",
        "European Grand Prix": "19",
        "San Marino Grand Prix": "24",
        "Spanish Grand Prix": "7",
        "Monaco Grand Prix": "25",
        "Canadian Grand Prix": "23",
        "French Grand Prix": "21",
        "British Grand Prix": "7",
        "German Grand Prix": "3",
        "Hungarian Grand Prix": "7",
        "Belgian Grand Prix": "11",
        "Italian Grand Prix": "17",
        "Portuguese Grand Prix": "19",
        "Japanese Grand Prix": "7",
        "Australian Grand Prix": "9"
      }
    },
    "1994": {
      "year": "1994",
      "positions": {
        "Brazilian Grand Prix": "18",
        "Pacific Grand Prix": "26",
        "San Marino Grand Prix": "9",
        "Monaco Grand Prix": "17",
        "Spanish Grand Prix": "3",
        "Canadian Grand Prix": "10",
        "French Grand Prix": "10",
        "British Grand Prix": "20",
        "German Grand Prix": "17",
        "Hungarian Grand Prix": "5",
        "Belgian Grand Prix": "5",
        "Italian Grand Prix": "15",
        "Portuguese Grand Prix": "18",
        "European Grand Prix": "13",
        "Japanese Grand Prix": "14",
        "Australian Grand Prix": "14"
      }
    },
    "1995": {
      "year": "1995",
      "positions": {
        "Brazilian Grand Prix": "6",
        "Argentine Grand Prix": "20",
        "Monaco Grand Prix": "5",
        "Canadian Grand Prix": "15",
        "French Grand Prix": "11",
        "British Grand Prix": "5",
        "German Grand Prix": "16",
        "Hungarian Grand Prix": "16",
        "Belgian Grand Prix": "5",
        "Italian Grand Prix": "4",
        "Portuguese Grand Prix": "9",
        "European Grand Prix": "23",
        "Pacific Grand Prix": "9",
        "Japanese Grand Prix": "7",
        "Australian Grand Prix": "4"
      }
    }
  },
  "qualiPosition": {
    "1991": {
      "year": "1991",
      "positions": {}
    },
    "1993": {
      "year": "1993",
      "positions": {}
    },
    "1994": {
      "year": "1994",
      "positions": {
        "Brazilian Grand Prix": "12",
        "Pacific Grand Prix": "12",
        "San Marino Grand Prix": "12",
        "Spanish Grand Prix": "11",
        "Canadian Grand Prix": "13",
        "French Grand Prix": "17",
        "British Grand Prix": "11",
        "German Grand Prix": "7",
        "Hungarian Grand Prix": "11",
        "Belgian Grand Prix": "12",
        "Italian Grand Prix": "21",
        "Portuguese Grand Prix": "12",
        "European Grand Prix": "14",
        "Japanese Grand Prix": "13",
        "Australian Grand Prix": "13"
      }
    },
    "1995": {
      "year": "1995",
      "positions": {
        "Brazilian Grand Prix": "9",
        "Argentine Grand Prix": "17",
        "Monaco Grand Prix": "10",
        "Canadian Grand Prix": "10",
        "French Grand Prix": "13",
        "British Grand Prix": "10",
        "German Grand Prix": "8",
        "Hungarian Grand Prix": "13",
        "Belgian Grand Prix": "6",
        "Italian Grand Prix": "9",
        "Portuguese Grand Prix": "12",
        "European Grand Prix": "10",
        "Pacific Grand Prix": "10",
        "Japanese Grand Prix": "24",
        "Australian Grand Prix": "10"
      }
    }
  },
  "driverQualifyingTimes": {
    "1991": {
      "year": "1991",
      "QualiTimes": {}
    },
    "1993": {
      "year": "1993",
      "QualiTimes": {}
    },
    "1994": {
      "year": "1994",
      "QualiTimes": {
        "Brazilian Grand Prix": [
          "1:18.246",
          "N/A",
          "N/A"
        ],
        "Pacific Grand Prix": [
          "1:12.751",
          "N/A",
          "N/A"
        ],
        "San Marino Grand Prix": [
          "1:23.703",
          "N/A",
          "N/A"
        ],
        "Spanish Grand Prix": [
          "1:23.981",
          "N/A",
          "N/A"
        ],
        "Canadian Grand Prix": [
          "1:28.579",
          "N/A",
          "N/A"
        ],
        "French Grand Prix": [
          "1:18.381",
          "N/A",
          "N/A"
        ],
        "British Grand Prix": [
          "1:26.920",
          "N/A",
          "N/A"
        ],
        "German Grand Prix": [
          "1:45.474",
          "N/A",
          "N/A"
        ],
        "Hungarian Grand Prix": [
          "1:20.984",
          "N/A",
          "N/A"
        ],
        "Belgian Grand Prix": [
          "2:24.048",
          "N/A",
          "N/A"
        ],
        "Italian Grand Prix": [
          "1:26.574",
          "N/A",
          "N/A"
        ],
        "Portuguese Grand Prix": [
          "1:22.288",
          "N/A",
          "N/A"
        ],
        "European Grand Prix": [
          "1:24.770",
          "N/A",
          "N/A"
        ],
        "Japanese Grand Prix": [
          "1:39.266",
          "N/A",
          "N/A"
        ],
        "Australian Grand Prix": [
          "1:18.237",
          "N/A",
          "N/A"
        ]
      }
    },
    "1995": {
      "year": "1995",
      "QualiTimes": {
        "Brazilian Grand Prix": [
          "1:21.779",
          "N/A",
          "N/A"
        ],
        "Argentine Grand Prix": [
          "1:58.660",
          "N/A",
          "N/A"
        ],
        "Monaco Grand Prix": [
          "1:24.933",
          "N/A",
          "N/A"
        ],
        "Canadian Grand Prix": [
          "1:29.641",
          "N/A",
          "N/A"
        ],
        "French Grand Prix": [
          "1:20.527",
          "N/A",
          "N/A"
        ],
        "British Grand Prix": [
          "1:30.453",
          "N/A",
          "N/A"
        ],
        "German Grand Prix": [
          "1:46.221",
          "N/A",
          "N/A"
        ],
        "Hungarian Grand Prix": [
          "1:20.640",
          "N/A",
          "N/A"
        ],
        "Belgian Grand Prix": [
          "1:56.622",
          "N/A",
          "N/A"
        ],
        "Italian Grand Prix": [
          "1:26.472",
          "N/A",
          "N/A"
        ],
        "Portuguese Grand Prix": [
          "1:22.914",
          "N/A",
          "N/A"
        ],
        "European Grand Prix": [
          "1:20.909",
          "N/A",
          "N/A"
        ],
        "Pacific Grand Prix": [
          "1:15.652",
          "N/A",
          "N/A"
        ],
        "Japanese Grand Prix": [
          "16:42.640",
          "N/A",
          "N/A"
        ],
        "Australian Grand Prix": [
          "N/A",
          "N/A",
          "N/A"
        ]
      }
    }
  },
  "totalWins": 0,
  "totalPodiums": 3,
  "totalPoles": 0
}