{
  "driverId": "gaillard",
  "finalStandings": {
    "1979": {
      "year": "1979",
      "position": "31",
      "points": "0"
    }
  },
  "posAfterRace": {
    "1979": {
      "year": "1979",
      "pos": {
        "French Grand Prix": {
          "points": 0
        },
        "British Grand Prix": {
          "points": 0
        },
        "German Grand Prix": {
          "points": 0
        },
        "Austrian Grand Prix": {
          "points": 0
        },
        "Dutch Grand Prix": {
          "points": 0
        }
      }
    }
  },
  "racePosition": {
    "1979": {
      "year": "1979",
      "positions": {
        "French Grand Prix": "26",
        "British Grand Prix": "13",
        "German Grand Prix": "25",
        "Austrian Grand Prix": "12",
        "Dutch Grand Prix": "25"
      }
    }
  },
  "qualiPosition": {
    "1979": {
      "year": "1979",
      "positions": {}
    }
  },
  "driverQualifyingTimes": {
    "1979": {
      "year": "1979",
      "QualiTimes": {}
    }
  },
  "totalWins": 0,
  "totalPodiums": 0,
  "totalPoles": 0
}