{
  "driverId": "gardner",
  "lastUpdate": "2024-06-13T18:09:58.063Z",
  "totalWins": 0,
  "totalPodiums": 0,
  "totalPoles": 0,
  "seasonWins": {
    "1964": 0,
    "1965": 0,
    "1968": 0
  },
  "seasonPodiums": {
    "1964": 0,
    "1965": 0,
    "1968": 0
  },
  "seasonPoles": {
    "1964": 0,
    "1965": 0,
    "1968": 0
  },
  "poles": {
    "1964": {},
    "1965": {},
    "1968": {}
  },
  "podiums": {
    "1964": {},
    "1965": {},
    "1968": {}
  },
  "fastLaps": {
    "1964": {},
    "1965": {},
    "1968": {}
  },
  "finalStandings": {
    "1964": {
      "year": "1964",
      "position": "39",
      "points": "0"
    },
    "1965": {
      "year": "1965",
      "position": "18",
      "points": "0"
    },
    "1968": {
      "year": "1968",
      "position": "42",
      "points": "0"
    }
  },
  "posAfterRace": {
    "1964": {
      "year": "1964",
      "pos": {
        "British Grand Prix": {
          "points": 0
        }
      }
    },
    "1965": {
      "year": "1965",
      "pos": {
        "South African Grand Prix": {
          "points": 0
        },
        "Monaco Grand Prix": {
          "points": 0
        },
        "Belgian Grand Prix": {
          "points": 0
        },
        "British Grand Prix": {
          "points": 0
        },
        "Dutch Grand Prix": {
          "points": 0
        },
        "German Grand Prix": {
          "points": 0
        },
        "Italian Grand Prix": {
          "points": 0
        }
      }
    },
    "1968": {
      "year": "1968",
      "pos": {
        "Italian Grand Prix": {
          "points": 0
        }
      }
    }
  },
  "racePosition": {
    "1964": {
      "year": "1964",
      "positions": {
        "British Grand Prix": "23"
      }
    },
    "1965": {
      "year": "1965",
      "positions": {
        "South African Grand Prix": "12",
        "Monaco Grand Prix": "14",
        "Belgian Grand Prix": "19",
        "British Grand Prix": "8",
        "Dutch Grand Prix": "11",
        "German Grand Prix": "19",
        "Italian Grand Prix": "16"
      }
    },
    "1968": {
      "year": "1968",
      "positions": {
        "Italian Grand Prix": "21"
      }
    }
  },
  "qualiPosition": {
    "1964": {
      "year": "1964",
      "positions": {}
    },
    "1965": {
      "year": "1965",
      "positions": {}
    },
    "1968": {
      "year": "1968",
      "positions": {}
    }
  },
  "driverQualifyingTimes": {
    "1964": {
      "year": "1964",
      "QualiTimes": {}
    },
    "1965": {
      "year": "1965",
      "QualiTimes": {}
    },
    "1968": {
      "year": "1968",
      "QualiTimes": {}
    }
  }
}