{
    "driverId": "klerk",
    "lastUpdate": "2024-08-03T03:38:31.487546",
    "totalWins": 0,
    "totalPodiums": 0,
    "totalPoles": 0,
    "totalDNFs": 2,
    "seasonWins": {
        "1963": 0,
        "1965": 0,
        "1969": 0,
        "1970": 0
    },
    "seasonPodiums": {
        "1963": 0,
        "1965": 0,
        "1969": 0,
        "1970": 0
    },
    "seasonPoles": {
        "1963": 0,
        "1965": 0,
        "1969": 0,
        "1970": 0
    },
    "seasonDNFs": {
        "1963": 1,
        "1965": 0,
        "1969": 1,
        "1970": 0
    },
    "poles": {
        "1963": [],
        "1965": [],
        "1969": [],
        "1970": []
    },
    "podiums": {
        "1963": {},
        "1965": {},
        "1969": {},
        "1970": {}
    },
    "DNFs": {
        "1963": {
            "South African Grand Prix": "Gearbox"
        },
        "1965": {},
        "1969": {
            "South African Grand Prix": "Not classified"
        },
        "1970": {}
    },
    "fastLaps": {
        "1963": {},
        "1965": {},
        "1969": {},
        "1970": {}
    },
    "finalStandings": {
        "1963": {
            "year": "1963",
            "position": "42",
            "points": "0"
        },
        "1965": {
            "year": "1965",
            "position": "24",
            "points": "0"
        },
        "1969": {
            "year": "1969",
            "position": "23",
            "points": "0"
        },
        "1970": {
            "year": "1970",
            "position": "31",
            "points": "0"
        }
    },
    "posAfterRace": {
        "1963": {
            "year": "1963",
            "pos": {
                "South African Grand Prix": {
                    "points": 0
                }
            }
        },
        "1965": {
            "year": "1965",
            "pos": {
                "South African Grand Prix": {
                    "points": 0
                }
            }
        },
        "1969": {
            "year": "1969",
            "pos": {
                "South African Grand Prix": {
                    "points": 0
                }
            }
        },
        "1970": {
            "year": "1970",
            "pos": {
                "South African Grand Prix": {
                    "points": 0
                }
            }
        }
    },
    "racePosition": {
        "1963": {
            "year": "1963",
            "positions": {
                "South African Grand Prix": "15"
            }
        },
        "1965": {
            "year": "1965",
            "positions": {
                "South African Grand Prix": "10"
            }
        },
        "1969": {
            "year": "1969",
            "positions": {
                "South African Grand Prix": "9"
            }
        },
        "1970": {
            "year": "1970",
            "positions": {
                "South African Grand Prix": "11"
            }
        }
    },
    "qualiPosition": {
        "1963": {
            "year": "1963",
            "positions": {}
        },
        "1965": {
            "year": "1965",
            "positions": {}
        },
        "1969": {
            "year": "1969",
            "positions": {}
        },
        "1970": {
            "year": "1970",
            "positions": {}
        }
    },
    "driverQualifyingTimes": {
        "1963": {
            "year": "1963",
            "QualiTimes": {}
        },
        "1965": {
            "year": "1965",
            "QualiTimes": {}
        },
        "1969": {
            "year": "1969",
            "QualiTimes": {}
        },
        "1970": {
            "year": "1970",
            "QualiTimes": {}
        }
    },
    "consistency": {
        "mean": {
            "wins": 0.0,
            "podiums": 0.0,
            "poles": 0.0,
            "points": 0.0
        },
        "std": {
            "wins": 0.0,
            "podiums": 0.0,
            "poles": 0.0,
            "points": 0.0
        },
        "cv": {
            "wins": 0,
            "podiums": 0,
            "poles": 0,
            "points": 0
        }
    },
    "peakSeason": {
        "wins": {
            "season": "No peak season",
            "wins": 0
        },
        "podiums": {
            "season": "No peak season",
            "podiums": 0
        },
        "poles": {
            "season": "No peak season",
            "poles": 0
        }
    },
    "avgRacePositions": {
        "1963": 15.0,
        "1965": 10.0,
        "1969": 9.0,
        "1970": 11.0
    },
    "avgQualiPositions": {
        "1963": -1,
        "1965": -1,
        "1969": -1,
        "1970": -1
    },
    "rates": {
        "wins": {
            "1963": 0.0,
            "1965": 0.0,
            "1969": 0.0,
            "1970": 0.0
        },
        "podiums": {
            "1963": 0.0,
            "1965": 0.0,
            "1969": 0.0,
            "1970": 0.0
        },
        "poles": {
            "1963": 0.0,
            "1965": 0.0,
            "1969": 0.0,
            "1970": 0.0
        },
        "DNFs": {
            "1963": 1.0,
            "1965": 1.0,
            "1969": 1.0,
            "1970": 1.0
        }
    },
    "winRate": 0.0,
    "podiumRate": 0.0,
    "poleRate": 0.0,
    "dnfRate": 0.5,
    "ptwConRate": {
        "1963": -1,
        "1965": -1,
        "1969": -1,
        "1970": -1
    },
    "positionsGainLost": {
        "1963": {},
        "1965": {},
        "1969": {},
        "1970": {}
    }
}