{
  "driverId": "legat",
  "finalStandings": {
    "1952": {
      "year": "1952",
      "position": "59",
      "points": "0"
    },
    "1953": {
      "year": "1953",
      "position": "89",
      "points": "0"
    }
  },
  "posAfterRace": {
    "1952": {
      "year": "1952",
      "pos": {
        "Belgian Grand Prix": {
          "points": 0
        }
      }
    },
    "1953": {
      "year": "1953",
      "pos": {
        "Belgian Grand Prix": {
          "points": 0
        }
      }
    }
  },
  "racePosition": {
    "1952": {
      "year": "1952",
      "positions": {
        "Belgian Grand Prix": "13"
      }
    },
    "1953": {
      "year": "1953",
      "positions": {
        "Belgian Grand Prix": "20"
      }
    }
  },
  "qualiPosition": {
    "1952": {
      "year": "1952",
      "positions": {}
    },
    "1953": {
      "year": "1953",
      "positions": {}
    }
  },
  "driverQualifyingTimes": {
    "1952": {
      "year": "1952",
      "QualiTimes": {}
    },
    "1953": {
      "year": "1953",
      "QualiTimes": {}
    }
  },
  "totalWins": 0,
  "totalPodiums": 0,
  "totalPoles": 0
}