[
    {
        "driverId": "antonelli",
        "permanentNumber": "12",
        "code": "ANT",
        "url": "https://en.wikipedia.org/wiki/Andrea_Kimi_Antonelli",
        "givenName": "Andrea Kimi",
        "familyName": "Antonelli",
        "dateOfBirth": "2006-08-25",
        "nationality": "Italian"
    },
    {
        "driverId": "russell",
        "permanentNumber": "63",
        "code": "RUS",
        "url": "http://en.wikipedia.org/wiki/George_Russell_(racing_driver)",
        "givenName": "George",
        "familyName": "Russell",
        "dateOfBirth": "1998-02-15",
        "nationality": "British"
    }
]