[
    {
        "driverId": "cesaris",
        "url": "http://en.wikipedia.org/wiki/Andrea_de_Cesaris",
        "givenName": "Andrea",
        "familyName": "de Cesaris",
        "dateOfBirth": "1959-05-31",
        "nationality": "Italian"
    },
    {
        "driverId": "hesnault",
        "url": "http://en.wikipedia.org/wiki/Fran%C3%A7ois_Hesnault",
        "givenName": "François",
        "familyName": "Hesnault",
        "dateOfBirth": "1956-12-30",
        "nationality": "French"
    }
]