[
    {
        "driverId": "colapinto",
        "permanentNumber": "43",
        "code": "COL",
        "url": "http://en.wikipedia.org/wiki/Franco_Colapinto",
        "givenName": "Franco",
        "familyName": "Colapinto",
        "dateOfBirth": "2003-05-27",
        "nationality": "Argentine"
    },
    {
        "driverId": "doohan",
        "permanentNumber": "7",
        "code": "DOO",
        "url": "http://en.wikipedia.org/wiki/Jack_Doohan",
        "givenName": "Jack",
        "familyName": "Doohan",
        "dateOfBirth": "2003-01-20",
        "nationality": "Australian"
    },
    {
        "driverId": "gasly",
        "permanentNumber": "10",
        "code": "GAS",
        "url": "http://en.wikipedia.org/wiki/Pierre_Gasly",
        "givenName": "Pierre",
        "familyName": "Gasly",
        "dateOfBirth": "1996-02-07",
        "nationality": "French"
    }
]